[
  {
    "title": "Sm\u00F6rg\u00E5sbord",
    "description": "This list is the modular buffet table of the very best mods available for 7 Days to Die.",
    "author": "FNS",
    "maintainers": [
      "github/Fluffernuttersandwich"
    ],
    "game": "sevendaystodie",
    "official": false,
    "tags": [
      "QoL",
      "Vanilla\u002B"
    ],
    "nsfw": false,
    "utility_list": false,
    "image_contains_title": true,
    "DisplayVersionOnlyInInstallerView": false,
    "force_down": false,
    "links": {
      "image": "https://raw.githubusercontent.com/Fluffernuttersandwich/Better7D2DbyFNS/refs/heads/main/Smorgasbord/Smorg1.jpg",
      "readme": "https://github.com/Fluffernuttersandwich/Better7D2DbyFNS/blob/main/README.md",
      "download": "https://authored-files.wabbajack.org/Sm\u00F6rg\u00E5sbord.wabbajack_512b6e25-c893-43ea-8786-c8f7091e221e",
      "machineURL": "Better7D2D",
      "discordURL": "https://discord.gg/WpVPJWj7Xk",
      "websiteURL": ""
    },
    "download_metadata": {
      "Hash": "0T9U/fFYZKI=",
      "Size": 170551157,
      "NumberOfArchives": 555,
      "SizeOfArchives": 31401681113,
      "NumberOfInstalledFiles": 52531,
      "SizeOfInstalledFiles": 45528078307,
      "TotalSize": 76929759420
    },
    "version": "2.3.1.3",
    "dateCreated": "1970-01-01T00:00:00Z",
    "dateUpdated": "2025-09-14T14:22:14.7445639Z",
    "repositoryName": ""
  }
]