[
  {
    "title": "Sm\u00F6rg\u00E5sbord",
    "description": "This list is the modular buffet table of the very best mods available for 7 Days to Die.",
    "author": "FNS",
    "maintainers": [
      "github/Fluffernuttersandwich"
    ],
    "game": "sevendaystodie",
    "official": false,
    "tags": [
      "QoL",
      "Vanilla\u002B"
    ],
    "nsfw": false,
    "utility_list": false,
    "image_contains_title": true,
    "DisplayVersionOnlyInInstallerView": false,
    "force_down": false,
    "links": {
      "image": "https://raw.githubusercontent.com/Fluffernuttersandwich/Better7D2DbyFNS/refs/heads/main/Smorgasbord/Smorg1.jpg",
      "readme": "https://github.com/Fluffernuttersandwich/Better7D2DbyFNS/blob/main/README.md",
      "download": "https://authored-files.wabbajack.org/Sm\u00F6rg\u00E5sbord.wabbajack_979515cd-4177-430a-929b-600796919ee5",
      "machineURL": "Better7D2D",
      "discordURL": "https://discord.gg/WpVPJWj7Xk",
      "websiteURL": ""
    },
    "download_metadata": {
      "Hash": "3YrTBz7DSqA=",
      "Size": 303203971,
      "NumberOfArchives": 443,
      "SizeOfArchives": 27386837393,
      "NumberOfInstalledFiles": 47101,
      "SizeOfInstalledFiles": 37741435996,
      "TotalSize": 65128273389
    },
    "version": "2.0.1",
    "dateCreated": "1970-01-01T00:00:00Z",
    "dateUpdated": "2025-07-04T23:06:23.1209991Z",
    "repositoryName": ""
  }
]
